llmeasy/__init__.py
llmeasy/base.py
llmeasy/core.py
llmeasy/providers/__init__.py
llmeasy/providers/base.py
llmeasy/providers/claude.py
llmeasy/providers/gemini.py
llmeasy/providers/grok.py
llmeasy/providers/mistral.py
llmeasy/providers/openai.py
llmeasy/templates/__init__.py
llmeasy/templates/template_parser.py
llmeasy/utils/__init__.py
llmeasy/utils/config.py
llmeasy/utils/json_helper.py
llmeasy-0.1.5.dist-info/METADATA
llmeasy-0.1.5.dist-info/WHEEL
llmeasy-0.1.5.dist-info/RECORD
