Metadata-Version: 2.1
Name: llmeasy
Version: 0.1.5
Summary: Easy to use LLM interface
License: Apache-2.0
Author: Kevin Wong
Author-email: kevinchwong@gmail.com
Requires-Python: >=3.9,<4.0
Classifier: License :: OSI Approved :: Apache Software License
Classifier: Programming Language :: Python :: 3
Classifier: Programming Language :: Python :: 3.9
Classifier: Programming Language :: Python :: 3.10
Classifier: Programming Language :: Python :: 3.11
Classifier: Programming Language :: Python :: 3.12
Classifier: Programming Language :: Python :: 3.13
Requires-Dist: aiohttp (>=3.9.3,<4.0.0)
Requires-Dist: anthropic (>=0.18.1,<0.19.0)
Requires-Dist: google-generativeai (>=0.3.2,<0.4.0)
Requires-Dist: mistralai (>=0.0.12,<0.0.13)
Requires-Dist: openai (>=1.12.0,<2.0.0)
Requires-Dist: python-dotenv (>=1.0.1,<2.0.0)
Requires-Dist: pyyaml (>=6.0.1,<7.0.0)
Requires-Dist: typing-extensions (>=4.9.0,<5.0.0)
